reait/__init__.py
reait/api.py
reait/main.py
reait-1.2.6.dist-info/licenses/LICENSE
reait-1.2.6.dist-info/METADATA
reait-1.2.6.dist-info/WHEEL
reait-1.2.6.dist-info/entry_points.txt
reait-1.2.6.dist-info/top_level.txt
reait-1.2.6.dist-info/RECORD
