Metadata-Version: 2.4
Name: reait
Version: 1.2.6
Summary: RevEng.AI Toolkit and Python API
Home-page: https://github.com/RevEng-AI/reait
Author: James Patrick-Evans
Author-email: James Patrick-Evans <james@reveng.ai>
Maintainer-email: James Patrick-Evans <james@reveng.ai>
License:                     GNU GENERAL PUBLIC LICENSE
Project-URL: Homepage, https://github.com/RevEng-AI/reait
Project-URL: Bug Tracker, https://github.com/RevEng-AI/reait/issues
Project-URL: Organisation Homepage, https://reveng.ai
Project-URL: Documentation, https://docs.reveng.ai
Keywords: reverse,engineering,reveng.ai,reveng,machine,learning,binary,analysis,ml,ai,vector,embedding
Platform: Cross Platform
Classifier: Programming Language :: Python :: 3
Classifier: License :: OSI Approved :: GNU General Public License v3 (GPLv3)
Classifier: Operating System :: OS Independent
Requires-Python: >=3.10
License-File: LICENSE
Requires-Dist: lief==0.16.4
Requires-Dist: numpy==2.2.4
Requires-Dist: pandas==2.2.3
Requires-Dist: Requests==2.32.3
Requires-Dist: rich==13.9.4
Requires-Dist: scikit_learn==1.6.1
Requires-Dist: scipy==1.15.2
Requires-Dist: setuptools==65.5.0
Requires-Dist: tomli==2.2.1
Dynamic: author
Dynamic: home-page
Dynamic: license-file
Dynamic: platform
